[{"title":"他我军军军军铺","describe":"儿童画到公司","thumbnail":"value","action":0,"type":0,"display_mode":0,"album":["sfdsf.png","reijgjji.png","sdojoj.png"],"browse_num":2845,"flag":0},{"title":"肉体上股份散","describe":"热辣辣改了哪里老奶奶了两年来了","thumbnail":"value","action":0,"type":0,"display_mode":1,"album":["sfdsf.png","reijgjji.png","sdojoj.png"],"browse_num":5477,"flag":3},{"title":"无污染同生共死","describe":"下班V型供电公司各位是否归属感发傻","thumbnail":"value","action":0,"type":0,"display_mode":2,"album":["sfdsf.png","reijgjji.png","sdojoj.png"],"browse_num":3678,"flag":0},{"title":"文物局统一同一款","describe":"强迫岁那年就往哪里女all你老娘啦","thumbnail":"value","action":0,"type":0,"display_mode":3,"album":["sfdsf.png","reijgjji.png","sdojoj.png"],"browse_num":2567,"flag":2}]